<?xml version="1.0" encoding="windows-1251"?> 
<grades>
     <subject>
          <Студенты> Степанян </Студенты>
          <Посещаемость> 75% </Посещаемость>
     </subject>
     <subject>
          <Студенты> Федорычев </Студенты>
          <Посещаемость> 50% </Посещаемость>
     </subject>
     <subject>
          <Студенты> Камалдинова </Студенты>
          <Посещаемость> 100% </Посещаемость>
     </subject>
     <subject>
          <Студенты> Вьюшкова </Студенты>
          <Посещаемость> 100% </Посещаемость>
     </subject>

</grades>
<?xml-stylesheet type="text/css" href="Sample.css"?>